baize/__init__.py
baize/const.py
baize/metrics.py
baize/extlib/__init__.py
baize/extlib/bucketing.py
baize/mxnet/__init__.py
baize/mxnet/modelzoo/__init__.py
baize/mxnet/modelzoo/layer/__init__.py
baize/mxnet/modelzoo/layer/attention.py
baize/mxnet/modelzoo/layer/embedding.py
baize/mxnet/modelzoo/layer/highway.py
baize/mxnet/modelzoo/loss/PairwiseLoss.py
baize/mxnet/modelzoo/loss/__init__.py
baize/mxnet/modelzoo/network/TextCNN.py
baize/mxnet/modelzoo/network/TransE.py
baize/mxnet/modelzoo/network/__init__.py
baize/mxnet/utils/__init__.py
baize/torch/__init__.py
baize/torch/functional/__init__.py
baize/torch/functional/rnn.py
baize/torch/functional/seq.py
baize/torch/functional/utils.py
baize/torch/nn/__init__.py
baize/torch/nn/ega.py
baize/utils/__init__.py
baize/utils/bucketing.py
baize/utils/padder.py
tests/__init__.py
PyBaize-0.0.7.dist-info/LICENSE
PyBaize-0.0.7.dist-info/METADATA
PyBaize-0.0.7.dist-info/WHEEL
PyBaize-0.0.7.dist-info/top_level.txt
PyBaize-0.0.7.dist-info/RECORD
