Metadata-Version: 2.1
Name: PyBaize
Version: 0.0.7
Summary: UNKNOWN
Home-page: UNKNOWN
License: UNKNOWN
Platform: UNKNOWN
Classifier: Programming Language :: Python :: 3.6
Classifier: Programming Language :: Python :: 3.7
Classifier: Programming Language :: Python :: 3.8
Classifier: Programming Language :: Python :: 3.9
Classifier: Environment :: Other Environment
Classifier: Intended Audience :: Developers
Classifier: License :: OSI Approved :: Mozilla Public License 2.0 (MPL 2.0)
Classifier: Operating System :: OS Independent
Classifier: Topic :: Software Development :: Libraries :: Python Modules
License-File: LICENSE
Requires-Dist: longling[ml] (>=1.3.35)
Requires-Dist: nni (>=1.8)
Provides-Extra: full
Requires-Dist: mxnet ; extra == 'full'
Requires-Dist: torch ; extra == 'full'
Provides-Extra: mxnet
Requires-Dist: mxnet ; extra == 'mxnet'
Provides-Extra: test
Requires-Dist: pytest (>=4) ; extra == 'test'
Requires-Dist: pytest-cov (>=2.6.0) ; extra == 'test'
Requires-Dist: pytest-flake8 ; extra == 'test'
Requires-Dist: mxnet ; extra == 'test'
Requires-Dist: torch ; extra == 'test'
Provides-Extra: torch
Requires-Dist: torch ; extra == 'torch'
